CHANGELOG.md
cq_electronics/__init__.py
cq_electronics/colors.py
cq_electronics/connectors/__init__.py
cq_electronics/connectors/headers.py
cq_electronics/connectors/rj45.py
cq_electronics/mechanical/__init__.py
cq_electronics/mechanical/din_rail.py
cq_electronics/rpi/rpi3b.py
cq_electronics/smd/__init__.py
cq_electronics/smd/bga.py
cq_electronics-0.1.0.dist-info/LICENSE
cq_electronics-0.1.0.dist-info/WHEEL
cq_electronics-0.1.0.dist-info/METADATA
cq_electronics-0.1.0.dist-info/RECORD
