Metadata-Version: 2.1
Name: cq-electronics
Version: 0.1.0
Summary: Pure CadQuery models of various electronic boards and components.
Home-page: https://github.com/sethfischer/cq-electronics
License: MIT
Keywords: cadquery,cq,cad,occt,electronics
Author: Seth Fischer
Author-email: seth@fischer.nz
Requires-Python: >=3.8,<3.11
Classifier: Development Status :: 1 - Planning
Classifier: Intended Audience :: Developers
Classifier: Intended Audience :: Manufacturing
Classifier: Intended Audience :: Science/Research
Classifier: License :: OSI Approved :: MIT License
Classifier: Operating System :: MacOS
Classifier: Operating System :: POSIX
Classifier: Operating System :: Unix
Classifier: Programming Language :: Python
Classifier: Programming Language :: Python :: 3
Classifier: Programming Language :: Python :: 3.10
Classifier: Programming Language :: Python :: 3.8
Classifier: Programming Language :: Python :: 3.9
Classifier: Topic :: Scientific/Engineering
Classifier: Topic :: Software Development :: Libraries :: Python Modules
Requires-Dist: cadquery (==2.2.0b0)
Requires-Dist: casadi (==3.5.5)
Project-URL: Bug Tracker, https://github.com/sethfischer/cq-electronics/issues
Project-URL: Documentation, https://cq-electronics.readthedocs.io
Project-URL: Repository, https://github.com/sethfischer/cq-electronics.git
